evatidevice/__init__.py
evatidevice/eva_tidevice.py
evatidevice/wrapper.py
evatidevice-0.0.4.dist-info/LICENSE
evatidevice-0.0.4.dist-info/METADATA
evatidevice-0.0.4.dist-info/WHEEL
evatidevice-0.0.4.dist-info/top_level.txt
evatidevice-0.0.4.dist-info/RECORD
