Metadata-Version: 2.1
Name: evatidevice
Version: 0.0.4
Summary: Add push folder function for tidevice.
Home-page: https://github.com/shizhao-git/evatidevice
Author: shizhao
Author-email: shizhao@mail.nwpu.edu.cn
License: UNKNOWN
Platform: UNKNOWN
License-File: LICENSE
Requires-Dist: tidevice
